{
  "planet": {
    "name": "Uranus",
    "generalInfo": {
      "description": "Uranus is the seventh planet from the Sun and the third-largest in the solar system. It is an ice giant primarily composed of hydrogen, helium, and water, ammonia, and methane ice.",
      "namesake": "Uranus is named after the ancient Greek god of the sky.",
      "age": "Uranus was discovered in 1781 by astronomer William Herschel."
    },
    "potentialForLife": {
      "description": "Uranus' extreme cold, high atmospheric pressure, and lack of a solid surface make it highly unlikely to support life.",
      "climateChangeImpact": "Uranus' atmosphere and conditions remain unaffected by human activities due to its distance and natural atmospheric dynamics."
    },
    "sizeAndDistance": {
      "diameter": "50,724 kilometers",
      "rank": "Third largest planet in the solar system",
      "distanceFromSun": {
        "value": "1.8 billion miles",
        "unit": "19.2 AU (astronomical units)"
      },
      "lightTravelTime": "2.7 hours"
    },
    "orbitAndRotation": {
      "rotationPeriod": "17.2 hours",
      "orbitPeriod": "84 Earth years",
      "leapYearExplanation": "Uranus does not experience leap years due to its long orbital period.",
      "axisTilt": "97.8 degrees",
      "seasonalEffects": "Uranus' extreme axial tilt causes it to experience dramatic seasonal variations over its 84-year orbit."
    },
    "moons": {
      "number": 27,
      "description": "Uranus has 27 known moons, named after characters from Shakespearean plays and Alexander Pope's poetry.",
      "origin": "The moons are believed to have formed from the same disk of gas and dust as the planet.",
      "averageDistance": "Varies significantly, with Miranda orbiting closest at about 80,000 miles.",
      "rankInSize": "Titania is the largest moon of Uranus and the eighth-largest in the solar system."
    },
    "rings": "Uranus has a thin and dark ring system composed of ice and rock particles.",
    "formation": {
      "description": "Uranus formed about 4.5 billion years ago from the primordial gas and dust cloud that shaped the solar system.",
      "layers": [
        {
          "name": "Core",
          "description": "A dense, rocky core with temperatures up to 9,000°F (5,000°C)."
        },
        {
          "name": "Mantle",
          "description": "A thick layer of water, ammonia, and methane ice surrounding the core."
        },
        {
          "name": "Atmosphere",
          "description": "An outer layer of hydrogen, helium, and methane gases, giving Uranus its blue-green color."
        }
      ]
    },
    "surface": {
      "features": "Uranus has no solid surface, with its outer layers composed of swirling gases and a slushy ocean of water, ammonia, and methane.",
      "oceanCoverage": "No oceans exist, but a 'slushy' mantle of water and ammonia ice lies beneath the atmosphere.",
      "volcanicActivity": "No volcanic activity is present, though its moon Miranda shows signs of past tectonic and cryovolcanic activity."
    },
    "atmosphere": {
      "composition": {
        "hydrogen": "82%",
        "helium": "15%",
        "methane": "2%",
        "other": "Trace amounts of ammonia and water vapor"
      },
      "protection": "The atmosphere provides no protection due to extreme conditions, including high pressures and low temperatures."
    },
    "magnetosphere": {
      "cause": "Generated by electric currents in the icy mantle of Uranus.",
      "effects": "Uranus' magnetic field is tilted and offset, causing unique auroras and interactions with solar wind.",
      "polarityReversal": "The magnetic field may undergo polarity reversals, though these are not well understood."
    }
  },
  "quizzes": [
    {
      "question": "What is the diameter of Uranus?",
      "options": ["31,518 miles", "50,000 miles", "12,742 miles", "100,000 miles"],
      "answer": "31,518 miles",
      "imagePath": "images/quiz/uranus_diameter.jpg"
    },
    {
      "question": "How long does it take Uranus to orbit the Sun?",
      "options": ["1 Earth year", "84 Earth years", "88 Earth days", "100 Earth years"],
      "answer": "84 Earth years",
      "imagePath": "images/quiz/uranus_orbit.jpg"
    },
    {
      "question": "What is Uranus named after?",
      "options": ["A Greek god", "A Roman god", "A Greek philosopher", "A constellation"],
      "answer": "A Greek god",
      "imagePath": "images/quiz/uranus_namesake.jpg"
    },
    {
      "question": "How far is Uranus from the Sun on average?",
      "options": ["1.8 billion miles", "778 million miles", "93 million miles", "500 million miles"],
      "answer": "1.8 billion miles",
      "imagePath": "images/quiz/uranus_distance.jpg"
    },
    {
      "question": "Does Uranus have any moons?",
      "options": ["Yes", "No"],
      "answer": "Yes",
      "imagePath": "images/quiz/uranus_moons.jpg"
    },
    {
      "question": "What is the temperature on Uranus during the day?",
      "options": ["-357°F", "-145°F", "-100°F", "43,000°F"],
      "answer": "-357°F",
      "imagePath": "images/quiz/uranus_temperature.jpg"
    },
    {
      "question": "How many Earth hours does a day on Uranus last?",
      "options": ["17.2", "24", "12", "36"],
      "answer": "17.2",
      "imagePath": "images/quiz/uranus_day_length.jpg"
    },
    {
      "question": "What is Uranus' orbit shape?",
      "options": ["Elliptical", "Circular", "Spiral", "Parabolic"],
      "answer": "Elliptical",
      "imagePath": "images/quiz/uranus_orbit_shape.jpg"
    },
    {
      "question": "How long does it take sunlight to travel from the Sun to Uranus?",
      "options": ["8 minutes", "43.3 minutes", "2.7 hours", "1 hour"],
      "answer": "2.7 hours",
      "imagePath": "images/quiz/uranus_light_travel.jpg"
    },
    {
      "question": "Why does Uranus experience extreme seasonal variation?",
      "options": ["It has an axial tilt of 97.8°", "It is a gas giant", "It is far from the Sun", "It has many moons"],
      "answer": "It has an axial tilt of 97.8°",
      "imagePath": "images/quiz/uranus_seasons.jpg"
    }
  ]
}
